add_noise_tool/__init__.py
add_noise_tool/main.py
nanobragg_noise-1.9.dist-info/licenses/LICENSE.txt
nanobragg_noise-1.9.dist-info/METADATA
nanobragg_noise-1.9.dist-info/WHEEL
nanobragg_noise-1.9.dist-info/entry_points.txt
nanobragg_noise-1.9.dist-info/top_level.txt
nanobragg_noise-1.9.dist-info/RECORD
