Metadata-Version: 2.4
Name: nanoBragg_noise
Version: 1.9
Summary: A command-line tool to add noise to simulated H5 data.
Author-email: Derek 'Braggling' Mendez <dermen@slac.stanford.edu>
License: MIT License
Classifier: Programming Language :: Python :: 3
Classifier: License :: OSI Approved :: MIT License
License-File: LICENSE.txt
Requires-Dist: numpy
Requires-Dist: h5py
Requires-Dist: joblib
Dynamic: license-file
